{"attributes": {"fullName": "criax.util.MaxNumber", "packageName": "criax.util", "isStatic": true, "type": "class", "name": "MaxNumber"}, "type": "class", "children": [{"attributes": {"text": "<p>Clase para las validacion de numeros maximo</p>"}, "type": "desc"}, {"attributes": {}, "type": "methods-static", "children": [{"attributes": {"line": 57, "isStatic": true, "name": "check"}, "type": "method", "children": [{"attributes": {}, "type": "params", "children": [{"attributes": {"name": "value"}, "type": "param", "children": [{"attributes": {"text": "<p>: valor del campo</p>"}, "type": "desc"}]}, {"attributes": {"name": "errorMessage"}, "type": "param", "children": [{"attributes": {"text": "<p>: mensaje de error</p>"}, "type": "desc"}, {"attributes": {}, "type": "types", "children": [{"attributes": {"type": "String"}, "type": "entry"}]}]}, {"attributes": {"defaultValue": "false", "optional": true, "name": "required"}, "type": "param", "children": [{"attributes": {"text": "<p>: si el campo es requerido [true-false]</p>"}, "type": "desc"}, {"attributes": {}, "type": "types", "children": [{"attributes": {"type": "Boolean"}, "type": "entry"}]}]}, {"attributes": {"name": "maxNumber"}, "type": "param", "children": [{"attributes": {"text": "<p>: numero maximo</p>"}, "type": "desc"}, {"attributes": {}, "type": "types", "children": [{"attributes": {"type": "Integer"}, "type": "entry"}]}]}, {"attributes": {"defaultValue": "false", "optional": true, "name": "decimals"}, "type": "param", "children": [{"attributes": {"text": "<p>: si se aceptan numeros decimales o no [true-false]</p>"}, "type": "desc"}, {"attributes": {}, "type": "types", "children": [{"attributes": {"type": "Boolean"}, "type": "entry"}]}]}]}, {"attributes": {"text": "<p>metodo para checkear la validacion</p>"}, "type": "desc"}, {"attributes": {}, "type": "throws", "children": [{"attributes": {"text": "<p>if value>maxNumber</p>", "type": "qx.core.ValidationError"}, "type": "desc"}]}, {"attributes": {}, "type": "return", "children": [{"attributes": {"text": "<p>si el campo es valido o no</p>"}, "type": "desc"}, {"attributes": {}, "type": "types", "children": [{"attributes": {"type": "Boolean"}, "type": "entry"}]}]}]}, {"attributes": {"line": 36, "isStatic": true, "name": "validate"}, "type": "method", "children": [{"attributes": {}, "type": "params", "children": [{"attributes": {"name": "errorMessage"}, "type": "param", "children": [{"attributes": {"text": "<p>: mensaje de error</p>"}, "type": "desc"}, {"attributes": {}, "type": "types", "children": [{"attributes": {"type": "String"}, "type": "entry"}]}]}, {"attributes": {"defaultValue": "false", "optional": true, "name": "required"}, "type": "param", "children": [{"attributes": {"text": "<p>: si el campo es requerido [true-false]</p>"}, "type": "desc"}, {"attributes": {}, "type": "types", "children": [{"attributes": {"type": "Boolean"}, "type": "entry"}]}]}, {"attributes": {"name": "maxNumber"}, "type": "param", "children": [{"attributes": {"text": "<p>: numero maximo</p>"}, "type": "desc"}, {"attributes": {}, "type": "types", "children": [{"attributes": {"type": "Integer"}, "type": "entry"}]}]}, {"attributes": {"defaultValue": "false", "optional": true, "name": "decimals"}, "type": "param", "children": [{"attributes": {"text": "<p>: si se aceptan numeros decimales o no [true-false]</p>"}, "type": "desc"}, {"attributes": {}, "type": "types", "children": [{"attributes": {"type": "Boolean"}, "type": "entry"}]}]}]}, {"attributes": {"text": "<p>metodo para validar que el dato pasado sea menor que el numero pasado</p>"}, "type": "desc"}, {"attributes": {}, "type": "return", "children": [{"attributes": {"text": "<p>si el campo es valido o no</p>"}, "type": "desc"}, {"attributes": {}, "type": "types", "children": [{"attributes": {"type": "Boolean"}, "type": "entry"}]}]}]}]}]}