{"attributes": {"fullName": "criax.mobile.toolbar.BottomBar", "packageName": "criax.mobile.toolbar", "type": "class", "name": "BottomBar", "superClass": "qx.ui.mobile.container.Composite"}, "type": "class", "children": [{"attributes": {"text": "<p>Una barra de herramientas con botones</p>\n\n<p>Here is a little example of how to use the widget.\nEl parametro es una constante segun la cual se muestra el tipo de grupo\nGroupButton.GRAY\nGroupButton.WHITE\nGroupButton.GREEN \nGroupButton.BLACK</p>\n\n<pre class=\"javascript\">\n  var bottombar = new criax.mobile.toolbar.BottomBar(criax.mobile.toolbar.BottomBar.BLACK);\n  bottombar.addButton(new criax.mobile.form.Button(\"button 1\"),{flex:1});\n  bottombar.addButton(new criax.mobile.form.Button(\"button 2\"),{flex:1});\n  bottombar.addButton(new criax.mobile.form.Button(\"button 3\"),{flex:1});\n\n  this.addContent(bottombar);\n</pre>"}, "type": "desc"}, {"attributes": {}, "type": "constructor", "children": [{"attributes": {"line": 38, "isCtor": true, "overriddenFrom": "qx.ui.mobile.container.Composite", "name": "ctor"}, "type": "method", "children": [{"attributes": {}, "type": "params", "children": [{"attributes": {"defaultValue": "null", "optional": true, "name": "type"}, "type": "param", "children": [{"attributes": {"text": "<p>tipo de BottomBar (GRAY, <span class=\"caps\">WHITE</span>, <span class=\"caps\">GREEN</span>, <span class=\"caps\">BLACK</span>)</p>"}, "type": "desc"}, {"attributes": {}, "type": "types", "children": [{"attributes": {"type": "String"}, "type": "entry"}]}]}]}, {"attributes": {"text": "<p>metodo de inicializacion de la clase</p>"}, "type": "desc"}]}]}, {"attributes": {}, "type": "constants", "children": [{"attributes": {"type": "String", "name": "GRAY", "value": "navigationbar-gray"}, "type": "constant", "children": [{"attributes": {"text": ""}, "type": "desc"}]}, {"attributes": {"type": "String", "name": "WHITE", "value": "navigationbar-white"}, "type": "constant", "children": [{"attributes": {"text": ""}, "type": "desc"}]}, {"attributes": {"type": "String", "name": "GREEN", "value": "navigationbar-green"}, "type": "constant", "children": [{"attributes": {"text": ""}, "type": "desc"}]}, {"attributes": {"type": "String", "name": "BLACK", "value": "navigationbar-black"}, "type": "constant", "children": [{"attributes": {"text": ""}, "type": "desc"}]}]}, {"attributes": {}, "type": "methods", "children": [{"attributes": {"line": 91, "name": "addButton"}, "type": "method", "children": [{"attributes": {}, "type": "params", "children": [{"attributes": {"name": "button"}, "type": "param", "children": [{"attributes": {"text": "<p>boton agregar con evento y todo</p>"}, "type": "desc"}, {"attributes": {}, "type": "types", "children": [{"attributes": {"type": "qx.ui.mobile.form.Button"}, "type": "entry"}]}]}, {"attributes": {"defaultValue": "{flex:1", "optional": true, "name": "layoutProperties"}, "type": "param", "children": [{"attributes": {"text": "<p>} caracteristicas a ponerle al widget cuando se muestre</p>"}, "type": "desc"}, {"attributes": {}, "type": "types", "children": [{"attributes": {"type": "Map"}, "type": "entry"}]}]}]}, {"attributes": {"text": "<p>metodo para agregar los botones</p>"}, "type": "desc"}, {"attributes": {}, "type": "return", "children": [{"attributes": {"text": "<p>para agregar los botons en cadena</p>"}, "type": "desc"}, {"attributes": {}, "type": "types", "children": [{"attributes": {"type": "this"}, "type": "entry"}]}]}]}]}]}